kasearch/__init__.py
kasearch/align_sequences.py
kasearch/anarci_numbering.py
kasearch/canonical_alignment.py
kasearch/easy_search.py
kasearch/identity_calculations.py
kasearch/initiate_db.py
kasearch/kasearch.py
kasearch/merge_db.py
kasearch/meta_extract.py
kasearch/prepare_OASdb.py
kasearch/prepare_db.py
kasearch-0.0.20.dist-info/LICENSE
kasearch-0.0.20.dist-info/METADATA
kasearch-0.0.20.dist-info/WHEEL
kasearch-0.0.20.dist-info/top_level.txt
kasearch-0.0.20.dist-info/RECORD
