Metadata-Version: 2.1
Name: kasearch
Version: 0.0.20
Summary: KA-Search: Rapid and exhaustive sequence identity search of known antibodies
Maintainer: Tobias Hegelund Olsen; Brennan Abanades kenyon
License: BSD 3-clause license
License-File: LICENSE
Requires-Dist: pandas
Requires-Dist: joblib
Requires-Dist: requests
Requires-Dist: numpy
Requires-Dist: jax
Requires-Dist: jaxlib
